aiochsa/__init__.py
aiochsa/client.py
aiochsa/compiler.py
aiochsa/dialect.py
aiochsa/error_codes.py
aiochsa/exc.py
aiochsa/parser.py
aiochsa/pool.py
aiochsa/py.typed
aiochsa/record.py
aiochsa/sql.py
aiochsa/type.lark
aiochsa/types.py
aiochsa-1.2.2.dist-info/LICENSE
aiochsa-1.2.2.dist-info/METADATA
aiochsa-1.2.2.dist-info/WHEEL
aiochsa-1.2.2.dist-info/top_level.txt
aiochsa-1.2.2.dist-info/RECORD
