Metadata-Version: 2.1
Name: aiochsa
Version: 1.2.2
Summary: Clickhouse Python/asyncio library for use with SQLAlchemy core
Home-page: https://github.com/ods/aiochsa
Author: Denis Otkidach
Author-email: denis.otkidach@gmail.com
License: MIT
Platform: UNKNOWN
Classifier: Development Status :: 5 - Production/Stable
Classifier: Intended Audience :: Developers
Classifier: License :: OSI Approved :: MIT License
Classifier: Programming Language :: Python :: 3.7
Classifier: Programming Language :: Python :: 3.8
Classifier: Programming Language :: Python :: 3.9
Classifier: Programming Language :: Python :: 3.10
Classifier: Topic :: Database :: Front-Ends
Requires-Python: >=3.7
License-File: LICENSE
Requires-Dist: aiohttp (<4.0.0,>=3.7.2)
Requires-Dist: clickhouse-sqlalchemy (<0.2.0,>=0.1.5)
Requires-Dist: lark-parser (>=0.11.2)
Requires-Dist: simplejson (>=3.16.0)
Requires-Dist: sqlalchemy (<1.4.0,>=1.3.0)
Requires-Dist: backports.zoneinfo ; python_version < "3.9"
Provides-Extra: dev
Requires-Dist: lovely-pytest-docker (>=0.3.0) ; extra == 'dev'
Requires-Dist: pytest (>=6.2.0) ; extra == 'dev'
Requires-Dist: pytest-asyncio (>=0.17.0) ; extra == 'dev'
Requires-Dist: pytest-cov (>=2.11.1) ; extra == 'dev'
